Workbook

Sheet Summary
A1: NINELIVES — item pool (v7.08)
A2: Generated from items.js by tools/build-item-list.mjs + tools/build-item-workbook.py. Every count below is a live COUNTIF over the 'All Items' sheet, so edits there re-total. Counts cover ACTIVE items only — 41 retired items live on the 'Inactive' sheet.
A4: BY CLASS
A5: Class | B5: Total | C5: common | D5: uncommon | E5: rare | F5: starting | G5: gated
A6: Stickers | B6: =COUNTIF('All Items'!$A$2:$A$133,$A6) | C6: =COUNTIFS('All Items'!$A$2:$A$133,$A6,'All Items'!$G$2:$G$133,"common") | D6: =COUNTIFS('All Items'!$A$2:$A$133,$A6,'All Items'!$G$2:$G$133,"uncommon") | E6: =COUNTIFS('All Items'!$A$2:$A$133,$A6,'All Items'!$G$2:$G$133,"rare") | F6: =COUNTIFS('All Items'!$A$2:$A$133,$A6,'All Items'!$I$2:$I$133,"yes") | G6: =COUNTIFS('All Items'!$A$2:$A$133,$A6,'All Items'!$I$2:$I$133,"no")
A7: Pillars | B7: =COUNTIF('All Items'!$A$2:$A$133,$A7) | C7: =COUNTIFS('All Items'!$A$2:$A$133,$A7,'All Items'!$G$2:$G$133,"common") | D7: =COUNTIFS('All Items'!$A$2:$A$133,$A7,'All Items'!$G$2:$G$133,"uncommon") | E7: =COUNTIFS('All Items'!$A$2:$A$133,$A7,'All Items'!$G$2:$G$133,"rare") | F7: =COUNTIFS('All Items'!$A$2:$A$133,$A7,'All Items'!$I$2:$I$133,"yes") | G7: =COUNTIFS('All Items'!$A$2:$A$133,$A7,'All Items'!$I$2:$I$133,"no")
A8: Bases | B8: =COUNTIF('All Items'!$A$2:$A$133,$A8) | C8: =COUNTIFS('All Items'!$A$2:$A$133,$A8,'All Items'!$G$2:$G$133,"common") | D8: =COUNTIFS('All Items'!$A$2:$A$133,$A8,'All Items'!$G$2:$G$133,"uncommon") | E8: =COUNTIFS('All Items'!$A$2:$A$133,$A8,'All Items'!$G$2:$G$133,"rare") | F8: =COUNTIFS('All Items'!$A$2:$A$133,$A8,'All Items'!$I$2:$I$133,"yes") | G8: =COUNTIFS('All Items'!$A$2:$A$133,$A8,'All Items'!$I$2:$I$133,"no")
A9: Same-Powers | B9: =COUNTIF('All Items'!$A$2:$A$133,$A9) | C9: =COUNTIFS('All Items'!$A$2:$A$133,$A9,'All Items'!$G$2:$G$133,"common") | D9: =COUNTIFS('All Items'!$A$2:$A$133,$A9,'All Items'!$G$2:$G$133,"uncommon") | E9: =COUNTIFS('All Items'!$A$2:$A$133,$A9,'All Items'!$G$2:$G$133,"rare") | F9: =COUNTIFS('All Items'!$A$2:$A$133,$A9,'All Items'!$I$2:$I$133,"yes") | G9: =COUNTIFS('All Items'!$A$2:$A$133,$A9,'All Items'!$I$2:$I$133,"no")
A10: Cursed Stickers | B10: =COUNTIF('All Items'!$A$2:$A$133,$A10) | C10: =COUNTIFS('All Items'!$A$2:$A$133,$A10,'All Items'!$G$2:$G$133,"common") | D10: =COUNTIFS('All Items'!$A$2:$A$133,$A10,'All Items'!$G$2:$G$133,"uncommon") | E10: =COUNTIFS('All Items'!$A$2:$A$133,$A10,'All Items'!$G$2:$G$133,"rare") | F10: =COUNTIFS('All Items'!$A$2:$A$133,$A10,'All Items'!$I$2:$I$133,"yes") | G10: =COUNTIFS('All Items'!$A$2:$A$133,$A10,'All Items'!$I$2:$I$133,"no")
A11: Packs | B11: =COUNTIF('All Items'!$A$2:$A$133,$A11) | C11: =COUNTIFS('All Items'!$A$2:$A$133,$A11,'All Items'!$G$2:$G$133,"common") | D11: =COUNTIFS('All Items'!$A$2:$A$133,$A11,'All Items'!$G$2:$G$133,"uncommon") | E11: =COUNTIFS('All Items'!$A$2:$A$133,$A11,'All Items'!$G$2:$G$133,"rare") | F11: =COUNTIFS('All Items'!$A$2:$A$133,$A11,'All Items'!$I$2:$I$133,"yes") | G11: =COUNTIFS('All Items'!$A$2:$A$133,$A11,'All Items'!$I$2:$I$133,"no")
A12: All items | B12: =SUM(B6:B11) | C12: =SUM(C6:C11) | D12: =SUM(D6:D11) | E12: =SUM(E6:E11) | F12: =SUM(F6:F11) | G12: =SUM(G6:G11)
A15: BY OUTCOME (what the item pays you in)
A16: Outcome | B16: Stickers | C16: Pillars | D16: Bases | E16: Same-Powers | F16: Cursed Stickers | G16: Packs | H16: Total
A17: Bury | B17: =COUNTIFS('All Items'!$B$2:$B$133,$A17,'All Items'!$A$2:$A$133,"Stickers") | C17: =COUNTIFS('All Items'!$B$2:$B$133,$A17,'All Items'!$A$2:$A$133,"Pillars") | D17: =COUNTIFS('All Items'!$B$2:$B$133,$A17,'All Items'!$A$2:$A$133,"Bases") | E17: =COUNTIFS('All Items'!$B$2:$B$133,$A17,'All Items'!$A$2:$A$133,"Same-Powers") | F17: =COUNTIFS('All Items'!$B$2:$B$133,$A17,'All Items'!$A$2:$A$133,"Cursed Stickers") | G17: =COUNTIFS('All Items'!$B$2:$B$133,$A17,'All Items'!$A$2:$A$133,"Packs") | H17: =COUNTIF('All Items'!$B$2:$B$133,$A17)
A18: Card Change | B18: =COUNTIFS('All Items'!$B$2:$B$133,$A18,'All Items'!$A$2:$A$133,"Stickers") | C18: =COUNTIFS('All Items'!$B$2:$B$133,$A18,'All Items'!$A$2:$A$133,"Pillars") | D18: =COUNTIFS('All Items'!$B$2:$B$133,$A18,'All Items'!$A$2:$A$133,"Bases") | E18: =COUNTIFS('All Items'!$B$2:$B$133,$A18,'All Items'!$A$2:$A$133,"Same-Powers") | F18: =COUNTIFS('All Items'!$B$2:$B$133,$A18,'All Items'!$A$2:$A$133,"Cursed Stickers") | G18: =COUNTIFS('All Items'!$B$2:$B$133,$A18,'All Items'!$A$2:$A$133,"Packs") | H18: =COUNTIF('All Items'!$B$2:$B$133,$A18)
A19: Coin Gain | B19: =COUNTIFS('All Items'!$B$2:$B$133,$A19,'All Items'!$A$2:$A$133,"Stickers") | C19: =COUNTIFS('All Items'!$B$2:$B$133,$A19,'All Items'!$A$2:$A$133,"Pillars") | D19: =COUNTIFS('All Items'!$B$2:$B$133,$A19,'All Items'!$A$2:$A$133,"Bases") | E19: =COUNTIFS('All Items'!$B$2:$B$133,$A19,'All Items'!$A$2:$A$133,"Same-Powers") | F19: =COUNTIFS('All Items'!$B$2:$B$133,$A19,'All Items'!$A$2:$A$133,"Cursed Stickers") | G19: =COUNTIFS('All Items'!$B$2:$B$133,$A19,'All Items'!$A$2:$A$133,"Packs") | H19: =COUNTIF('All Items'!$B$2:$B$133,$A19)
A20: Deal Control | B20: =COUNTIFS('All Items'!$B$2:$B$133,$A20,'All Items'!$A$2:$A$133,"Stickers") | C20: =COUNTIFS('All Items'!$B$2:$B$133,$A20,'All Items'!$A$2:$A$133,"Pillars") | D20: =COUNTIFS('All Items'!$B$2:$B$133,$A20,'All Items'!$A$2:$A$133,"Bases") | E20: =COUNTIFS('All Items'!$B$2:$B$133,$A20,'All Items'!$A$2:$A$133,"Same-Powers") | F20: =COUNTIFS('All Items'!$B$2:$B$133,$A20,'All Items'!$A$2:$A$133,"Cursed Stickers") | G20: =COUNTIFS('All Items'!$B$2:$B$133,$A20,'All Items'!$A$2:$A$133,"Packs") | H20: =COUNTIF('All Items'!$B$2:$B$133,$A20)
A21: Deck Removal | B21: =COUNTIFS('All Items'!$B$2:$B$133,$A21,'All Items'!$A$2:$A$133,"Stickers") | C21: =COUNTIFS('All Items'!$B$2:$B$133,$A21,'All Items'!$A$2:$A$133,"Pillars") | D21: =COUNTIFS('All Items'!$B$2:$B$133,$A21,'All Items'!$A$2:$A$133,"Bases") | E21: =COUNTIFS('All Items'!$B$2:$B$133,$A21,'All Items'!$A$2:$A$133,"Same-Powers") | F21: =COUNTIFS('All Items'!$B$2:$B$133,$A21,'All Items'!$A$2:$A$133,"Cursed Stickers") | G21: =COUNTIFS('All Items'!$B$2:$B$133,$A21,'All Items'!$A$2:$A$133,"Packs") | H21: =COUNTIF('All Items'!$B$2:$B$133,$A21)
A22: Loadout & Meta | B22: =COUNTIFS('All Items'!$B$2:$B$133,$A22,'All Items'!$A$2:$A$133,"Stickers") | C22: =COUNTIFS('All Items'!$B$2:$B$133,$A22,'All Items'!$A$2:$A$133,"Pillars") | D22: =COUNTIFS('All Items'!$B$2:$B$133,$A22,'All Items'!$A$2:$A$133,"Bases") | E22: =COUNTIFS('All Items'!$B$2:$B$133,$A22,'All Items'!$A$2:$A$133,"Same-Powers") | F22: =COUNTIFS('All Items'!$B$2:$B$133,$A22,'All Items'!$A$2:$A$133,"Cursed Stickers") | G22: =COUNTIFS('All Items'!$B$2:$B$133,$A22,'All Items'!$A$2:$A$133,"Packs") | H22: =COUNTIF('All Items'!$B$2:$B$133,$A22)
A23: Pack | B23: =COUNTIFS('All Items'!$B$2:$B$133,$A23,'All Items'!$A$2:$A$133,"Stickers") | C23: =COUNTIFS('All Items'!$B$2:$B$133,$A23,'All Items'!$A$2:$A$133,"Pillars") | D23: =COUNTIFS('All Items'!$B$2:$B$133,$A23,'All Items'!$A$2:$A$133,"Bases") | E23: =COUNTIFS('All Items'!$B$2:$B$133,$A23,'All Items'!$A$2:$A$133,"Same-Powers") | F23: =COUNTIFS('All Items'!$B$2:$B$133,$A23,'All Items'!$A$2:$A$133,"Cursed Stickers") | G23: =COUNTIFS('All Items'!$B$2:$B$133,$A23,'All Items'!$A$2:$A$133,"Packs") | H23: =COUNTIF('All Items'!$B$2:$B$133,$A23)
A24: Peek | B24: =COUNTIFS('All Items'!$B$2:$B$133,$A24,'All Items'!$A$2:$A$133,"Stickers") | C24: =COUNTIFS('All Items'!$B$2:$B$133,$A24,'All Items'!$A$2:$A$133,"Pillars") | D24: =COUNTIFS('All Items'!$B$2:$B$133,$A24,'All Items'!$A$2:$A$133,"Bases") | E24: =COUNTIFS('All Items'!$B$2:$B$133,$A24,'All Items'!$A$2:$A$133,"Same-Powers") | F24: =COUNTIFS('All Items'!$B$2:$B$133,$A24,'All Items'!$A$2:$A$133,"Cursed Stickers") | G24: =COUNTIFS('All Items'!$B$2:$B$133,$A24,'All Items'!$A$2:$A$133,"Packs") | H24: =COUNTIF('All Items'!$B$2:$B$133,$A24)
A25: Pile Size & Score | B25: =COUNTIFS('All Items'!$B$2:$B$133,$A25,'All Items'!$A$2:$A$133,"Stickers") | C25: =COUNTIFS('All Items'!$B$2:$B$133,$A25,'All Items'!$A$2:$A$133,"Pillars") | D25: =COUNTIFS('All Items'!$B$2:$B$133,$A25,'All Items'!$A$2:$A$133,"Bases") | E25: =COUNTIFS('All Items'!$B$2:$B$133,$A25,'All Items'!$A$2:$A$133,"Same-Powers") | F25: =COUNTIFS('All Items'!$B$2:$B$133,$A25,'All Items'!$A$2:$A$133,"Cursed Stickers") | G25: =COUNTIFS('All Items'!$B$2:$B$133,$A25,'All Items'!$A$2:$A$133,"Packs") | H25: =COUNTIF('All Items'!$B$2:$B$133,$A25)
A26: Safety & Saves | B26: =COUNTIFS('All Items'!$B$2:$B$133,$A26,'All Items'!$A$2:$A$133,"Stickers") | C26: =COUNTIFS('All Items'!$B$2:$B$133,$A26,'All Items'!$A$2:$A$133,"Pillars") | D26: =COUNTIFS('All Items'!$B$2:$B$133,$A26,'All Items'!$A$2:$A$133,"Bases") | E26: =COUNTIFS('All Items'!$B$2:$B$133,$A26,'All Items'!$A$2:$A$133,"Same-Powers") | F26: =COUNTIFS('All Items'!$B$2:$B$133,$A26,'All Items'!$A$2:$A$133,"Cursed Stickers") | G26: =COUNTIFS('All Items'!$B$2:$B$133,$A26,'All Items'!$A$2:$A$133,"Packs") | H26: =COUNTIF('All Items'!$B$2:$B$133,$A26)
A27: Same Shield & Power | B27: =COUNTIFS('All Items'!$B$2:$B$133,$A27,'All Items'!$A$2:$A$133,"Stickers") | C27: =COUNTIFS('All Items'!$B$2:$B$133,$A27,'All Items'!$A$2:$A$133,"Pillars") | D27: =COUNTIFS('All Items'!$B$2:$B$133,$A27,'All Items'!$A$2:$A$133,"Bases") | E27: =COUNTIFS('All Items'!$B$2:$B$133,$A27,'All Items'!$A$2:$A$133,"Same-Powers") | F27: =COUNTIFS('All Items'!$B$2:$B$133,$A27,'All Items'!$A$2:$A$133,"Cursed Stickers") | G27: =COUNTIFS('All Items'!$B$2:$B$133,$A27,'All Items'!$A$2:$A$133,"Packs") | H27: =COUNTIF('All Items'!$B$2:$B$133,$A27)
A28: Shuffle | B28: =COUNTIFS('All Items'!$B$2:$B$133,$A28,'All Items'!$A$2:$A$133,"Stickers") | C28: =COUNTIFS('All Items'!$B$2:$B$133,$A28,'All Items'!$A$2:$A$133,"Pillars") | D28: =COUNTIFS('All Items'!$B$2:$B$133,$A28,'All Items'!$A$2:$A$133,"Bases") | E28: =COUNTIFS('All Items'!$B$2:$B$133,$A28,'All Items'!$A$2:$A$133,"Same-Powers") | F28: =COUNTIFS('All Items'!$B$2:$B$133,$A28,'All Items'!$A$2:$A$133,"Cursed Stickers") | G28: =COUNTIFS('All Items'!$B$2:$B$133,$A28,'All Items'!$A$2:$A$133,"Packs") | H28: =COUNTIF('All Items'!$B$2:$B$133,$A28)
... A38: Curse · Sticker Removal | B38: =COUNTIFS('All Items'!$B$2:$B$133,$A38,'All Items'!$A$2:$A$133,"Stickers") | C38: =COUNTIFS('All Items'!$B$2:$B$133,$A38,'All Items'!$A$2:$A$133,"Pillars") | D38: =COUNTIFS('All Items'!$B$2:$B$133,$A38,'All Items'!$A$2:$A$133,"Bases") | E38: =COUNTIFS('All Items'!$B$2:$B$133,$A38,'All Items'!$A$2:$A$133,"Same-Powers") | F38: =COUNTIFS('All Items'!$B$2:$B$133,$A38,'All Items'!$A$2:$A$133,"Cursed Stickers") | G38: =COUNTIFS('All Items'!$B$2:$B$133,$A38,'All Items'!$A$2:$A$133,"Packs") | H38: =COUNTIF('All Items'!$B$2:$B$133,$A38)
A39: All items | B39: =SUM(B17:B38) | C39: =SUM(C17:C38) | D39: =SUM(D17:D38) | E39: =SUM(E17:E38) | F39: =SUM(F17:F38) | G39: =SUM(G17:G38) | H39: =SUM(H17:H38)
A41: An item can pay in more than one currency; these counts use its PRIMARY outcome. The 'Also pays' column on 'All Items' carries the secondary ones.

Sheet All Items
A1: Class | B1: Outcome | C1: Outcome detail | D1: Also pays | E1: Item | F1: id | G1: Rarity | H1: Cost | I1: Unlocked at start | J1: Unlock type | K1: Unlock stat | L1: Unlock count | M1: Suit limit | N1: In-game help text | O1: Effect key | P1: Lint
A2: Stickers | B2: Card Change | C2: rank ± | E2: +1 Rank | F2: rankUp | G2: common | H2: 1 | I2: yes | N2: +1 rank (stops at Ace) | O2: rank
A3: Stickers | B3: Pile Size & Score | C3: score shelter | E3: Anchor | F3: anchor | G3: common | H3: 1 | I3: yes | N3: At deal end if top card → exclude from smallest-pile size | O3: anchor
A4: Stickers | B4: Card Change | C4: suit, chosen | E4: Change to ♠ | F4: changeSuitSpade | G4: common | H4: 1 | I4: yes | N4: Change to ♠ | O4: changeSuitTo
A5: Stickers | B5: Card Change | C5: suit, chosen | E5: Change to ♣ | F5: changeSuitClub | G5: common | H5: 1 | I5: yes | N5: Change to ♣ | O5: changeSuitTo
A6: Stickers | B6: Card Change | C6: suit, chosen | E6: Change to ♥ | F6: changeSuitHeart | G6: common | H6: 1 | I6: yes | N6: Change to ♥ | O6: changeSuitTo
A7: Stickers | B7: Card Change | C7: suit, chosen | E7: Change to ♦ | F7: changeSuitDiamond | G7: common | H7: 1 | I7: yes | N7: Change to ♦ | O7: changeSuitTo
A8: Stickers | B8: Card Change | C8: rank, random | E8: Random Rank | F8: randomFixedValue | G8: common | H8: 1 | I8: no | J8: milestone | K8: runsPlayed | L8: 3 | N8: Randomize rank | O8: randomFixedValue
A9: Stickers | B9: Card Change | C9: suit, random | E9: Random Suit | F9: changeSuitRandom | G9: common | H9: 1 | I9: yes | N9: Randomize suit | O9: changeSuitRandom
A10: Stickers | B10: Safety & Saves | C10: rank-matched tie save; curse on kill | E10: Same-Safe | F10: tieSafe | G10: common | H10: 1 | I10: yes | N10: If another pile shows this rank → safe If this card kills its pile → this becomes a curse | O10: tieSafe
A11: Stickers | B11: Card Change | C11: rank ± | E11: −1 Rank | F11: rankDown | G11: common | H11: 1 | I11: yes | N11: -1 rank (stops at 2) | O11: rank
A12: Stickers | B12: Card Change | C12: rank ± | E12: +2 Rank | F12: rankUp2 | G12: uncommon | H12: 3 | I12: no | J12: milestone | K12: dealsWonRegular | L12: 4 | N12: +2 rank (stops at Ace) | O12: rank
A13: Stickers | B13: Peek | C13: needs a base-free column | E13: Base Scout | F13: baseScout | G13: uncommon | H13: 3 | I13: no | J13: behavior | K13: basesPlaced | L13: 12 | N13: If in column with no Base → peek next card If this card kills its pile → this becomes a curse | O13: baseScout
A14: Stickers | B14: Coin Gain | C14: flat +1; curse on kill | E14: Bonus Coin | F14: gainCoin | G14: uncommon | H14: 3 | I14: yes | N14: +1 coin If this card kills its pile → this becomes a curse | O14: gainCoin
A15: Stickers | B15: Pile Size & Score | C15: equalises the board; curse on kill | E15: Donate | F15: donate | G15: uncommon | H15: 3 | I15: yes | N15: Make all pile sizes equal If this card kills its pile → this becomes a curse | O15: donate
A16: Stickers | B16: Safety & Saves | C16: carrier safe on a matched bet; curse on kill | E16: Guard | F16: suitImmunity | G16: uncommon | H16: 3 | I16: no | J16: behavior | K16: spadesPlayed | L16: 150 | N16: If another pile shows this suit → safe If this card kills its pile → this becomes a curse | O16: suitImmunity
A17: Stickers | B17: Coin Gain | C17: deal-end payout | E17: Payout | F17: extraCoin | G17: uncommon | H17: 3 | I17: no | J17: behavior | K17: perfectDeals | L17: 1 | N17: At deal end if top card → earn coins equal to pile size | O17: extraCoin
A18: Stickers | B18: Peek | C18: needs a pillar-free column | E18: Pillar Scout | F18: pillarScout | G18: uncommon | H18: 3 | I18: no | J18: behavior | K18: pillarsPlaced | L18: 12 | N18: If in column with no Pillar → peek next card If this card kills its pile → this becomes a curse | O18: pillarScout
A19: Stickers | B19: Bury | C19: on landing; curse on kill | E19: Quick Bury | F19: quickBury | G19: uncommon | H19: 3 | I19: yes | N19: Bury 1 card under this pile If this card kills its pile → this becomes a curse | O19: quickBury
A20: Stickers | B20: Same Shield & Power | C20: on landing; curse on kill | E20: Recharge Shield | F20: rechargeSameShield | G20: uncommon | H20: 3 | I20: no | J20: behavior | K20: correctSames | L20: 10 | N20: Charge Same Shield If this card kills its pile → this becomes a curse | O20: rechargeSameShield
A21: Stickers | B21: Shuffle | C21: offered on landing; curse on kill | E21: Ripple | F21: diamondSnob | G21: uncommon | H21: 3 | I21: no | J21: behavior | K21: removalsUsed | L21: 18 | N21: Optionally shuffle every pile topped by this suit If this card kills its pile → this becomes a curse | O21: diamondSnob
A22: Stickers | B22: Bury | C22: per-card growth; curse on kill | E22: Snowball Bury | F22: snowball | G22: uncommon | H22: 3 | I22: no | J22: behavior | K22: perfectDeals | L22: 6 | N22: Bury X cards, X = times this card has landed correctly If this card kills its pile → this becomes a curse | O22: snowball
A23: Stickers | B23: Coin Gain | C23: per-card growth; curse on kill | E23: Snowball Coins | F23: snowballCoins | G23: uncommon | H23: 3 | I23: no | J23: behavior | K23: perfectDeals | L23: 10 | N23: +X coins, X = times this card has landed correctly If this card kills its pile → this becomes a curse | O23: snowballCoins
A24: Stickers | B24: Same Shield & Power | C24: on landing; curse on kill | E24: Tap Power | F24: activateSamePower | G24: uncommon | H24: 3 | I24: no | J24: behavior | K24: correctSames | L24: 34 | N24: Fire Same-Power If this card kills its pile → this becomes a curse | O24: activateSamePower
A25: Stickers | B25: Tell | C25: this pile, next draw; curse on kill | E25: Tell | F25: tell | G25: uncommon | H25: 3 | I25: yes | N25: This card shows a tell (higher/lower/same) If this card kills its pile → this becomes a curse | O25: tell
A26: Stickers | B26: Peek | C26: on landing; curse on kill | E26: Twin Spark | F26: twinSpark | G26: uncommon | H26: 3 | I26: no | J26: behavior | K26: zenGamesPlayed | L26: 4 | N26: Peek next card If this card kills its pile → this becomes a curse | O26: twinSpark
A27: Stickers | B27: Card Change | C27: rank ± | E27: −2 Rank | F27: rankDown2 | G27: uncommon | H27: 3 | I27: no | J27: milestone | K27: dealsSurvived | L27: 12 | N27: -2 rank (stops at 2) | O27: rank
A28: Pillars | B28: Coin Gain | C28: per suit landing | E28: Heart Bonus | F28: heartBounty | G28: common | H28: 6 | I28: yes | N28: When a ♥ lands in this column → +1 coin | O28: suitBounty
A29: Pillars | B29: Loadout & Meta | C29: wards a Two; cleanses cursed landings | D29: Curse Removal | E29: Bouncer | F29: twoWard | G29: uncommon | H29: 6 | I29: no | J29: behavior | K29: jokersPlayed | L29: 4 | N29: 50% chance to turn away a Just a Two mystery 100% if your full deck has no 2s When a cursed card lands in this column → remove that curse from the card | O29: twoWard
A30: Pillars | B30: Store Economy | C30: Purge ladder climbs slower; deal-end +purges bought this climb | D30: Coin Gain | E30: Bulk Rate | F30: bulkRate | G30: uncommon | H30: 6 | I30: no | J30: behavior | K30: removalsUsed | L30: 16 | N30: The store's Purge price does not climb At deal end → +X coins, X = Purges bought this climb | O30: purgeStepDiscount
A31: Pillars | B31: Safety & Saves | C31: relaxes what survives a Same | D31: Same Shield & Power | E31: Close Call | F31: sameTolNear | G31: uncommon | H31: 6 | I31: no | J31: behavior | K31: correctSames | L31: 52 | N31: Same calls are safe on cards ±1 in value in this column — a survived Same counts as a full correct Same (charges the Same Shield, fires your Same-Power) | O31: sameTolerance
A32: Pillars | B32: Safety & Saves | C32: any tie, in column | E32: Column Tie-Safe | F32: columnTieSafe | G32: uncommon | H32: 6 | I32: no | J32: behavior | K32: samesCalled | L32: 12 | N32: Any tie is safe in this column | O32: columnTieSafe
A33: Pillars | B33: Coin Gain | C33: on the locked rank | E33: Crowd Favorite | F33: crowdFavorite | G33: uncommon | H33: 6 | I33: no | J33: milestone | K33: dealsSurvived | L33: 18 | N33: When a {rank} lands correctly in this column → +2 coins | O33: rankCoin | P33: TEMPLATE
A34: Pillars | B34: Bury | C34: on a cursed landing | D34: Peek, Curse Payoff | E34: Curse Harvest | F34: curseHarvest | G34: uncommon | H34: 6 | I34: yes | N34: When a cursed card lands in this column → bury 1 card under that pile, then peek next card | O34: curseBuryPeek
A35: Pillars | B35: Curse Removal | C35: prevention: no conversions in column | E35: Curse Ward | F35: stickerCurseWard | G35: uncommon | H35: 6 | I35: no | J35: behavior | K35: stickersApplied | L35: 40 | N35: Stickers in this column never convert into curses | O35: stickerCurseWard
A36: Pillars | B36: Bury | C36: sticker-heavy ♣ | E36: Dense Bury | F36: denseBury | G36: uncommon | H36: 6 | I36: no | J36: behavior | K36: stickersApplied | L36: 140 | N36: When a ♣ with 3+ stickers lands correctly in this column → bury 1 card under that pile | O36: denseBury
A37: Pillars | B37: Pile Size & Score | C37: ♦ tops excluded | E37: Diamond Anchor | F37: diamondAnchor | G37: uncommon | H37: 6 | I37: no | J37: behavior | K37: diamondsPlayed | L37: 200 | N37: At deal end → exclude each ♦-topped pile in this column from the smallest-pile score | O37: diamondAnchor
A38: Pillars | B38: Pile Size & Score | C38: equalises on a ♦ | E38: Diamond Distribution | F38: diamondDistribution | G38: uncommon | H38: 6 | I38: no | J38: behavior | K38: removalsUsed | L38: 10 | N38: When a ♦ lands in this column → make this column's piles equal size | O38: diamondDistribution
A39: Pillars | B39: Loadout & Meta | C39: mirrors the centre pillar | E39: Ditto | F39: ditto | G39: uncommon | H39: 6 | I39: no | J39: milestone | K39: runsWon | L39: 1 | N39: Mirror the center column's Pillar | O39: ditto
A40: Pillars | B40: Tell | C40: on an 8 | E40: Eight Ball | F40: eightPeek | G40: uncommon | H40: 6 | I40: yes | N40: When an 8 lands in this column → tell on that card | O40: eightTell
A41: Pillars | B41: Bury | C41: per empty rank | D41: Deck Shaping | E41: Empty Ranks Bury | F41: zeroRanksBury | G41: uncommon | H41: 6 | I41: no | J41: behavior | K41: removalsUsed | L41: 40 | N41: When a ♣ lands in this column → bury 1 card under that pile per rank with zero copies in your full deck | O41: clubZeroRanksBury
A42: Pillars | B42: Coin Gain | C42: per empty rank, most-held landing | D42: Deck Shaping | E42: Empty Ranks Coins | F42: heartZeroRanksCoin | G42: uncommon | H42: 6 | I42: no | J42: behavior | K42: removalsUsed | L42: 50 | N42: When your most-held rank ({rank}) lands in this column → +2 coins per rank with zero copies in your full deck | O42: heartZeroRanksCoin | P42: TEMPLATE
A43: Pillars | B43: Coin Gain | C43: per ♥ top at end | E43: Envy | F43: envy | G43: uncommon | H43: 6 | I43: no | J43: milestone | K43: runsPlayed | L43: 5 | N43: At deal end → +2 coins per pile in this column with a ♥ | O43: heartPiles
A44: Pillars | B44: Deck Removal | C44: the column's last death purges the killer | D44: Deck Shaping | E44: Final Cut | F44: finalPilePurge | G44: uncommon | H44: 6 | I44: no | J44: behavior | K44: pilesLost | L44: 50 | N44: When the last pile in this column dies → permanently purge the card that killed it | O44: finalPilePurge
A45: Pillars | B45: Store Economy | C45: one-time Purge halving on purchase; deal-end +current Purge price | D45: Coin Gain | E45: Flat Purge | F45: purgeFlatFive | G45: uncommon | H45: 6 | I45: yes | N45: On purchase → halve the store's Purge price (minimum 3) At deal end → +X coins, X = the store's current Purge price | O45: purgeHalve
A46: Pillars | B46: Sticker Grant | C46: chance, on landing | E46: Flypaper | F46: flypaper | G46: uncommon | H46: 6 | I46: no | J46: behavior | K46: stickersApplied | L46: 25 | N46: When a card lands correctly in this column → 5% chance it gains a random sticker | O46: flypaper
A47: Pillars | B47: Pile Size & Score | C47: an extra pile | E47: Fourth Seat | F47: fourthSeat | G47: uncommon | H47: 6 | I47: no | J47: milestone | K47: endlessStagesReached | L47: 1 | N47: This column starts each deal with 1 extra pile (max 4) | O47: columnPiles
A48: Pillars | B48: Store Economy | C48: one free shelf item; +1 per stickered landing | D48: Coin Gain | E48: Freebie | F48: freebie | G48: uncommon | H48: 6 | I48: no | J48: behavior | K48: pinkyTipsSeen | L48: 2 | N48: One random item in every store costs 0 When a stickered card lands in this column → +1 coin | O48: freebie
A49: Pillars | B49: Coin Gain | C49: only pillar equipped | D49: Loadout | E49: Greedy | F49: greedy | G49: uncommon | H49: 6 | I49: no | J49: milestone | K49: dealsSurvived | L49: 6 | N49: At deal end if only equipped pillar → +1 coin per 5 cards in your full deck | O49: greedy
A50: Pillars | B50: Coin Gain | C50: if all survive | E50: Guardian | F50: columnGuardian | G50: uncommon | H50: 6 | I50: yes | N50: At deal end if every pile in this column survived → +4 coins | O50: columnAllAlive
A51: Pillars | B51: Coin Gain | C51: if one pile survives | E51: Insurance | F51: insurance | G51: uncommon | H51: 6 | I51: no | J51: behavior | K51: pilesLost | L51: 55 | N51: At deal end if only one pile is alive → +8 coins | O51: insurance
A52: Pillars | B52: Coin Gain | C52: if none survive | E52: Last Licks | F52: lastLicks | G52: uncommon | H52: 6 | I52: no | J52: behavior | K52: pilesLost | L52: 18 | N52: At deal end if no pile in this column survived → +8 coins | O52: columnNoneAlive
A53: Pillars | B53: Peek | C53: on a pile death | E53: Last Rites | F53: lastRites | G53: uncommon | H53: 6 | I53: no | J53: behavior | K53: dealsWonLegendary | L53: 1 | N53: When a pile in this column dies → peek next card | O53: lastRites
A54: Pillars | B54: Safety & Saves | C54: majority suit | E54: Majority Rule | F54: suitMajoritySafe | G54: uncommon | H54: 6 | I54: no | J54: milestone | K54: bossesBeaten | L54: 6 | N54: If half or more of your full deck is {suit} → {suit} cards are safe when they land in this column | O54: suitMajoritySafe | P54: TEMPLATE
A55: Pillars | B55: Bury | C55: most-held rank, per empty rank | D55: Deck Shaping | E55: Most-Held Bury | F55: mostHeldRankBury | G55: uncommon | H55: 6 | I55: no | J55: behavior | K55: removalsUsed | L55: 45 | N55: When your most-held rank ({rank}) lands in this column → bury 1 card under that pile per rank with zero copies in your full deck | O55: mostHeldRankBury | P55: TEMPLATE
A56: Pillars | B56: Store Economy | C56: first restock + reshuffle free; +coins at deal end | D56: Coin Gain | E56: On the House | F56: firstFree | G56: uncommon | H56: 6 | I56: yes | N56: First restock of each store and first reshuffle of each deal are free. +2 coins at end of deal | O56: firstFree
A57: Pillars | B57: Pile Size & Score | C57: ♦ while broke; flat broke may purge | D57: Pauper, Deck Removal | E57: Pauper's Diamond | F57: pauperDiamondEqualize | G57: uncommon | H57: 6 | I57: yes | N57: If purse <10 coins → when a ♦ lands in this column make all piles the same size If 0 coins → optionally purge the top card of any pile board-wide | O57: pauperDiamondEqualize
A58: Pillars | B58: Bury | C58: while broke | D58: Pauper | E58: Pauper's Fattening | F58: pauperClub | G58: uncommon | H58: 6 | I58: yes | N58: If purse <10 coins → when a ♣ lands in this column bury 1 If 0 coins → bury 3 | O58: pauperClubBury
A59: Pillars | B59: Safety & Saves | C59: ♥ while broke; flat broke peeks | D59: Pauper, Peek | E59: Pauper's Heart | F59: pauperHeart | G59: uncommon | H59: 6 | I59: yes | N59: If purse <10 coins → when a ♥ lands in this column it is safe If 0 coins → peek next card | O59: pauperHeartSafe
A60: Pillars | B60: Tell | C60: while broke | D60: Pauper | E60: Pauper's Spade | F60: pauperSpade | G60: uncommon | H60: 6 | I60: yes | N60: If purse <10 coins → when a ♠ lands in this column it shows a tell If 0 coins → all piles show a tell | O60: pauperSpadeTell
A61: Pillars | B61: Peek | C61: on a royal ♠ | E61: Queen's Eye | F61: queensEye | G61: uncommon | H61: 6 | I61: yes | N61: When a royal ♠ (J/Q/K) lands in this column → peek next card | O61: queensEye
A62: Pillars | B62: Loadout & Meta | C62: finds the Queen; Queens pay on landing | D62: Coin Gain | E62: Queen-Finder | F62: queenFinder | G62: uncommon | H62: 6 | I62: no | J62: behavior | K62: jokersPlayed | L62: 6 | N62: +50% chance to find a Beheaded Queen at a mystery node 100% if Queens are your most-held rank When a Queen lands in this column → +1 coin | O62: queenFinder
A63: Pillars | B63: Safety & Saves | C63: neighbour rank at zero | D63: Deck Shaping | E63: Rank Gap | F63: rankGapSafe | G63: uncommon | H63: 6 | I63: no | J63: behavior | K63: removalsUsed | L63: 20 | N63: If a card lands in this column and your full deck holds zero copies of the rank above or below it → it is safe | O63: rankGapSafe
A64: Pillars | B64: Safety & Saves | C64: deck's commonest rank | E64: Rank Shield | F64: rankShield | G64: uncommon | H64: 6 | I64: yes | N64: The most common rank in your full deck ({rank}) is always safe in this column | O64: rankShield | P64: TEMPLATE
A65: Pillars | B65: Store Economy | C65: rares twice as often; +1 per stickered landing | D65: Coin Gain | E65: Rare Hunter | F65: rareHunter | G65: uncommon | H65: 6 | I65: no | J65: behavior | K65: pillarsPlaced | L65: 25 | N65: Rare items appear in the store twice as often When a stickered card lands in this column → +1 coin | O65: rareHunter
A66: Pillars | B66: Safety & Saves | C66: revive a dead pile | E66: Revive | F66: revive | G66: uncommon | H66: 6 | I66: no | J66: milestone | K66: dealsWonLegendary | L66: 4 | N66: When a pile in this column reaches 10 cards → revive one dead pile | O66: revive
A67: Pillars | B67: Safety & Saves | C67: relaxes what survives a Same | D67: Same Shield & Power | E67: Royal Pair | F67: sameTolRoyal | G67: uncommon | H67: 6 | I67: no | J67: behavior | K67: samesCalled | L67: 40 | N67: A royal landing on a royal survives a Same call in this column | O67: sameTolerance
A68: Pillars | B68: Safety & Saves | C68: royals, if no 2s in deck | E68: Royal Sanctuary | F68: royalSanctuary | G68: uncommon | H68: 6 | I68: no | J68: behavior | K68: removalsUsed | L68: 30 | N68: If your full deck has no 2s → royals (J/Q/K) are always safe in this column | O68: royalSafeNoTwos
A69: Pillars | B69: Safety & Saves | C69: relaxes what survives a Same | D69: Same Shield & Power | E69: Same Suit Safe | F69: sameTolSuit | G69: uncommon | H69: 6 | I69: yes | N69: A card landing on its own suit is safe in this column | O69: sameTolerance
A70: Pillars | B70: Safety & Saves | C70: deck's scarcest suit | E70: Scarce Suit | F70: suitShield | G70: uncommon | H70: 6 | I70: yes | N70: The suit your full deck holds the fewest of is safe when it lands in this column (ties → every tied suit) | O70: suitShieldDaily
A71: Pillars | B71: Safety & Saves | C71: chance to save a dying pile | E71: Second Wind | F71: secondWind | G71: uncommon | H71: 6 | I71: yes | N71: When a pile in this column dies → 25% chance to save it: the top card stays, the buried cards shuffle back into the deck | O71: secondWind
A72: Pillars | B72: Shuffle | C72: column, on a ♦ | E72: Shuffler | F72: royalCourt | G72: uncommon | H72: 6 | I72: yes | N72: When a ♦ lands in this column → optionally shuffle this column's piles | O72: shuffler
A73: Pillars | B73: Bury | C73: streak-gated | E73: Streak Bury | F73: streakTribute | G73: uncommon | H73: 6 | I73: no | J73: behavior | K73: cardsBuried | L73: 90 | N73: From the 4th consecutive correct guess in this column → bury 1 card per guess — resets on a wrong guess or a guess in another column | O73: streakTribute
A74: Pillars | B74: Coin Gain | C74: streak-grown | E74: Streak Coin | F74: streakCoin | G74: uncommon | H74: 6 | I74: yes | N74: From the 4th consecutive correct guess in this column → +1 coin per guess Resets on a wrong guess or a guess in another column | O74: streakCoin
A75: Pillars | B75: Bury | C75: on the locked rank | E75: Underdog | F75: underdog | G75: uncommon | H75: 6 | I75: no | J75: behavior | K75: cardsBuried | L75: 40 | N75: When a {rank} lands in this column → bury 1 card under that pile | O75: rankBury | P75: TEMPLATE
A76: Pillars | B76: Safety & Saves | C76: aces high or low | E76: Wild Aces | F76: wildAces | G76: uncommon | H76: 6 | I76: no | J76: behavior | K76: jokersPlayed | L76: 8 | N76: Aces count as high or low in this column | O76: wildAces
A77: Pillars | B77: Tell | C77: most-held rank | D77: Deck Shaping | E77: Most-Held Tell | F77: mostHeldRankTell | G77: rare | H77: 6 | I77: no | J77: behavior | K77: removalsUsed | L77: 25 | N77: When your most-held rank ({rank}) lands in this column → it shows a tell | O77: mostHeldRankTell | P77: TEMPLATE
A78: Bases | B78: Pile Size & Score | C78: equalises the whole board | E78: Ballast | F78: evenOut | G78: uncommon | H78: 6 | I78: yes | N78: Make every pile on the board equal size | O78: evenOut
A79: Bases | B79: Peek | C79: trades the deal's banked bonus | D79: Coin Loss | E79: Bonus Reset | F79: bonusResetPeek | G79: uncommon | H79: 6 | I79: no | J79: milestone | K79: coinsEarnedLifetime | L79: 80 | N79: Reset bonus coins earned this deal to 0 → peek next card | O79: bonusResetPeek
A80: Bases | B80: Card Change | C80: column tops → deck's commonest rank | E80: Chorus | F80: chorus | G80: uncommon | H80: 6 | I80: no | J80: milestone | K80: bestCampaignScore | L80: 160 | N80: Set every top card in this column to {rank} | O80: chorus | P80: TEMPLATE
A81: Bases | B81: Curse Removal | C81: strips curses in column | E81: Cleanse | F81: cleanseColumn | G81: uncommon | H81: 6 | I81: yes | N81: Remove all curses from this column's top cards | O81: cleanseColumn
A82: Bases | B82: Bury | C82: under each ♣ top | E82: Club Dig | F82: clubDig | G82: uncommon | H82: 6 | I82: no | J82: behavior | K82: clubsPlayed | L82: 250 | N82: Bury 1 card under each ♣-topped pile in this column | O82: suitDig
A83: Bases | B83: Tell | C83: each ♣ top in column | E83: Club Oracle | F83: clubOracle | G83: uncommon | H83: 6 | I83: no | J83: behavior | K83: clubsPlayed | L83: 90 | N83: Tell each ♣-topped pile in this column for the next draw (higher/lower/same) | O83: clubTell
A84: Bases | B84: Peek | C84: destroys this column's pillar | D84: Loadout | E84: Demolish | F84: demolish | G84: uncommon | H84: 6 | I84: no | J84: behavior | K84: pillarsPlaced | L84: 18 | N84: Permanently destroy this column's Pillar → peek the next 3 cards | O84: demolish
A85: Bases | B85: Coin Gain | C85: doubles bonus, adds a curse | D85: Curse Payoff | E85: Devil's Deal | F85: devilsDeal | G85: uncommon | H85: 6 | I85: yes | N85: Double bonus coins earned this deal → add a curse to a top card in this column | O85: devilsDeal
A86: Bases | B86: Peek | C86: spends the whole purse | E86: Empty Purse | F86: emptyPurse | G86: uncommon | H86: 6 | I86: no | J86: milestone | K86: coinsEarnedLifetime | L86: 150 | N86: Spend all your coins → bury 1 card per 5 coins spent, then peek the next card | O86: emptyPurse
A87: Bases | B87: Deal Control | C87: clears an ambush instantly | E87: Escape Hatch | F87: ambushOut | G87: uncommon | H87: 6 | I87: no | J87: behavior | K87: ambushesWon | L87: 3 | N87: If in a Just a Two ambush → clear the deal instantly | O87: ambushWin
A88: Bases | B88: Coin Gain | C88: kills ♥ piles for coins | D88: Pile Destruction | E88: Heart Demolish | F88: heartDemolish | G88: uncommon | H88: 6 | I88: no | J88: behavior | K88: heartsPlayed | L88: 90 | N88: Destroy every ♥-topped pile in this column → +4 coins per pile | O88: heartDemolish
A89: Bases | B89: Coin Gain | C89: per ♥ in the column's piles, buried included | E89: Heart Tax | F89: tax | G89: uncommon | H89: 6 | I89: yes | N89: +1 coin per ♥ card in this column's piles — every card, not just the tops | O89: tax
A90: Bases | B90: Peek | C90: kills a ♠ pile first | D90: Pile Destruction | E90: Kamikaze | F90: kamikaze | G90: uncommon | H90: 6 | I90: no | J90: milestone | K90: dealsWonLegendary | L90: 2 | N90: Kill a random ♠-topped pile in this column → peek the next 2 cards | O90: kamikaze
A91: Bases | B91: Deal Control | C91: buries the deck, wins the deal | D91: Bury | E91: Last Resort | F91: lastResort | G91: uncommon | H91: 6 | I91: no | J91: behavior | K91: pilesLost | L91: 75 | N91: If not a boss deal → bury the whole deck under a pile in this column and win instantly (destroys itself and any adjacent Base) | O91: lastResort
A92: Bases | B92: Peek | C92: peek the next card | E92: Lone Eye | F92: lonePeek | G92: uncommon | H92: 6 | I92: no | J92: behavior | K92: samesCalled | L92: 8 | N92: Peek the next card | O92: lonePeek
A93: Bases | B93: Bury | C93: per pile, its top's missing-neighbour ranks | D93: Deck Shaping | E93: Missing Rank Dig | F93: missingRankDig | G93: uncommon | H93: 6 | I93: no | J93: behavior | K93: removalsUsed | L93: 35 | N93: For each pile in this column → bury 1 card per neighbor rank of its top card missing from your full deck | O93: missingRankDig
A94: Bases | B94: Safety & Saves | C94: revive a dead pile | E94: Phoenix | F94: revive | G94: uncommon | H94: 6 | I94: yes | N94: Revive a random dead pile in this column — buried cards return to the deck | O94: reviveBase
A95: Bases | B95: Same Shield & Power | C95: on landing; curse on kill | E95: Power Surge | F95: activateSame | G95: uncommon | H95: 6 | I95: no | J95: behavior | K95: correctSames | L95: 44 | N95: Fire your Same-Power | O95: activateSamePower
A96: Bases | B96: Store Economy | C96: cuts the Purge price | E96: Purge Coupon | F96: purgeDiscount | G96: uncommon | H96: 6 | I96: no | J96: behavior | K96: removalsUsed | L96: 3 | N96: −1 to the store's Purge price per ♦-topped pile in this column (minimum 3) | O96: purgeDiscount
A97: Bases | B97: Card Change | C97: column tops → one rank | E97: Rank Setter | F97: setValue | G97: uncommon | H97: 6 | I97: no | J97: milestone | K97: runsWon | L97: 2 | N97: Permanently set this column's top cards to the bottom pile's rank | O97: setValue
A98: Bases | B98: Loadout & Meta | C98: recharges the other bases | E98: Reactor | F98: refreshBases | G98: uncommon | H98: 6 | I98: no | J98: behavior | K98: basesPlaced | L98: 25 | N98: Recharge your other two Bases | O98: refreshBases
A99: Bases | B99: Same Shield & Power | C99: on landing; curse on kill | E99: Recharge Cell | F99: rechargeSame | G99: uncommon | H99: 6 | I99: no | J99: milestone | K99: correctSames | L99: 28 | N99: Charge the Same Shield | O99: rechargeSameShield
A100: Bases | B100: Deck Removal | C100: the chosen top card | D100: Pile Destruction | E100: Sacrifice | F100: sacrifice | G100: uncommon | H100: 6 | I100: yes | N100: Choose a pile → purge its top card from your deck, then kill that pile | O100: sacrifice
...

Sheet By Outcome
A1: Class | B1: Outcome | C1: Outcome detail | D1: Also pays | E1: Item | F1: id | G1: Rarity | H1: Cost | I1: Unlocked at start | J1: Unlock type | K1: Unlock stat | L1: Unlock count | M1: Suit limit | N1: In-game help text | O1: Effect key | P1: Lint
A2: Bury (13)
A3: Stickers | B3: Bury | C3: on landing; curse on kill | E3: Quick Bury | F3: quickBury | G3: uncommon | H3: 3 | I3: yes | N3: Bury 1 card under this pile If this card kills its pile → this becomes a curse | O3: quickBury
A4: Stickers | B4: Bury | C4: per-card growth; curse on kill | E4: Snowball Bury | F4: snowball | G4: uncommon | H4: 3 | I4: no | J4: behavior | K4: perfectDeals | L4: 6 | N4: Bury X cards, X = times this card has landed correctly If this card kills its pile → this becomes a curse | O4: snowball
A5: Pillars | B5: Bury | C5: on a cursed landing | D5: Peek, Curse Payoff | E5: Curse Harvest | F5: curseHarvest | G5: uncommon | H5: 6 | I5: yes | N5: When a cursed card lands in this column → bury 1 card under that pile, then peek next card | O5: curseBuryPeek
A6: Pillars | B6: Bury | C6: sticker-heavy ♣ | E6: Dense Bury | F6: denseBury | G6: uncommon | H6: 6 | I6: no | J6: behavior | K6: stickersApplied | L6: 140 | N6: When a ♣ with 3+ stickers lands correctly in this column → bury 1 card under that pile | O6: denseBury
A7: Pillars | B7: Bury | C7: per empty rank | D7: Deck Shaping | E7: Empty Ranks Bury | F7: zeroRanksBury | G7: uncommon | H7: 6 | I7: no | J7: behavior | K7: removalsUsed | L7: 40 | N7: When a ♣ lands in this column → bury 1 card under that pile per rank with zero copies in your full deck | O7: clubZeroRanksBury
A8: Pillars | B8: Bury | C8: most-held rank, per empty rank | D8: Deck Shaping | E8: Most-Held Bury | F8: mostHeldRankBury | G8: uncommon | H8: 6 | I8: no | J8: behavior | K8: removalsUsed | L8: 45 | N8: When your most-held rank ({rank}) lands in this column → bury 1 card under that pile per rank with zero copies in your full deck | O8: mostHeldRankBury | P8: TEMPLATE
A9: Pillars | B9: Bury | C9: while broke | D9: Pauper | E9: Pauper's Fattening | F9: pauperClub | G9: uncommon | H9: 6 | I9: yes | N9: If purse <10 coins → when a ♣ lands in this column bury 1 If 0 coins → bury 3 | O9: pauperClubBury
A10: Pillars | B10: Bury | C10: streak-gated | E10: Streak Bury | F10: streakTribute | G10: uncommon | H10: 6 | I10: no | J10: behavior | K10: cardsBuried | L10: 90 | N10: From the 4th consecutive correct guess in this column → bury 1 card per guess — resets on a wrong guess or a guess in another column | O10: streakTribute
A11: Pillars | B11: Bury | C11: on the locked rank | E11: Underdog | F11: underdog | G11: uncommon | H11: 6 | I11: no | J11: behavior | K11: cardsBuried | L11: 40 | N11: When a {rank} lands in this column → bury 1 card under that pile | O11: rankBury | P11: TEMPLATE
A12: Bases | B12: Bury | C12: under each ♣ top | E12: Club Dig | F12: clubDig | G12: uncommon | H12: 6 | I12: no | J12: behavior | K12: clubsPlayed | L12: 250 | N12: Bury 1 card under each ♣-topped pile in this column | O12: suitDig
A13: Bases | B13: Bury | C13: per pile, its top's missing-neighbour ranks | D13: Deck Shaping | E13: Missing Rank Dig | F13: missingRankDig | G13: uncommon | H13: 6 | I13: no | J13: behavior | K13: removalsUsed | L13: 35 | N13: For each pile in this column → bury 1 card per neighbor rank of its top card missing from your full deck | O13: missingRankDig
A14: Bases | B14: Bury | C14: peels stickers to bury | D14: Sticker Removal | E14: Sticker Harvest | F14: stickerHarvest | G14: uncommon | H14: 6 | I14: no | J14: behavior | K14: stickersApplied | L14: 115 | N14: Choose a pile → bury 2 cards per sticker on its top card, then peel all those stickers | O14: stickerHarvest
A15: Same-Powers | B15: Bury | C15: under every pile (experiment) | E15: Burrow | F15: linkBury | G15: uncommon | H15: 10 | I15: no | J15: behavior | K15: samesCalled | L15: 30 | N15: Bury 1 card under every pile | O15: linkBury
A17: Card Change (14)
A18: Stickers | B18: Card Change | C18: rank ± | E18: +1 Rank | F18: rankUp | G18: common | H18: 1 | I18: yes | N18: +1 rank (stops at Ace) | O18: rank
A19: Stickers | B19: Card Change | C19: rank ± | E19: +2 Rank | F19: rankUp2 | G19: uncommon | H19: 3 | I19: no | J19: milestone | K19: dealsWonRegular | L19: 4 | N19: +2 rank (stops at Ace) | O19: rank
A20: Stickers | B20: Card Change | C20: suit, chosen | E20: Change to ♠ | F20: changeSuitSpade | G20: common | H20: 1 | I20: yes | N20: Change to ♠ | O20: changeSuitTo
A21: Stickers | B21: Card Change | C21: suit, chosen | E21: Change to ♣ | F21: changeSuitClub | G21: common | H21: 1 | I21: yes | N21: Change to ♣ | O21: changeSuitTo
A22: Stickers | B22: Card Change | C22: suit, chosen | E22: Change to ♥ | F22: changeSuitHeart | G22: common | H22: 1 | I22: yes | N22: Change to ♥ | O22: changeSuitTo
A23: Stickers | B23: Card Change | C23: suit, chosen | E23: Change to ♦ | F23: changeSuitDiamond | G23: common | H23: 1 | I23: yes | N23: Change to ♦ | O23: changeSuitTo
A24: Stickers | B24: Card Change | C24: rank, random | E24: Random Rank | F24: randomFixedValue | G24: common | H24: 1 | I24: no | J24: milestone | K24: runsPlayed | L24: 3 | N24: Randomize rank | O24: randomFixedValue
A25: Stickers | B25: Card Change | C25: suit, random | E25: Random Suit | F25: changeSuitRandom | G25: common | H25: 1 | I25: yes | N25: Randomize suit | O25: changeSuitRandom
A26: Stickers | B26: Card Change | C26: rank ± | E26: −1 Rank | F26: rankDown | G26: common | H26: 1 | I26: yes | N26: -1 rank (stops at 2) | O26: rank
A27: Stickers | B27: Card Change | C27: rank ± | E27: −2 Rank | F27: rankDown2 | G27: uncommon | H27: 3 | I27: no | J27: milestone | K27: dealsSurvived | L27: 12 | N27: -2 rank (stops at 2) | O27: rank
A28: Bases | B28: Card Change | C28: column tops → deck's commonest rank | E28: Chorus | F28: chorus | G28: uncommon | H28: 6 | I28: no | J28: milestone | K28: bestCampaignScore | L28: 160 | N28: Set every top card in this column to {rank} | O28: chorus | P28: TEMPLATE
A29: Bases | B29: Card Change | C29: column tops → one rank | E29: Rank Setter | F29: setValue | G29: uncommon | H29: 6 | I29: no | J29: milestone | K29: runsWon | L29: 2 | N29: Permanently set this column's top cards to the bottom pile's rank | O29: setValue
A30: Bases | B30: Card Change | C30: column tops → one suit | E30: Suit Setter | F30: setSuit | G30: uncommon | H30: 6 | I30: no | J30: milestone | K30: runsWon | L30: 3 | N30: Permanently set this column's top cards to the bottom pile's suit | O30: setSuit
A31: Same-Powers | B31: Card Change | C31: every alive top → the called rank | E31: Rank Flood | F31: rankFlood | G31: uncommon | H31: 10 | I31: no | J31: behavior | K31: samesCalled | L31: 60 | N31: Set the top card of every alive pile to this card's rank — a Joker on either side ranks them by the ranked card; Joker-on-Joker makes Aces | O31: rankFlood
A33: Coin Gain (16)
A34: Stickers | B34: Coin Gain | C34: flat +1; curse on kill | E34: Bonus Coin | F34: gainCoin | G34: uncommon | H34: 3 | I34: yes | N34: +1 coin If this card kills its pile → this becomes a curse | O34: gainCoin
A35: Stickers | B35: Coin Gain | C35: deal-end payout | E35: Payout | F35: extraCoin | G35: uncommon | H35: 3 | I35: no | J35: behavior | K35: perfectDeals | L35: 1 | N35: At deal end if top card → earn coins equal to pile size | O35: extraCoin
A36: Stickers | B36: Coin Gain | C36: per-card growth; curse on kill | E36: Snowball Coins | F36: snowballCoins | G36: uncommon | H36: 3 | I36: no | J36: behavior | K36: perfectDeals | L36: 10 | N36: +X coins, X = times this card has landed correctly If this card kills its pile → this becomes a curse | O36: snowballCoins
A37: Pillars | B37: Coin Gain | C37: on the locked rank | E37: Crowd Favorite | F37: crowdFavorite | G37: uncommon | H37: 6 | I37: no | J37: milestone | K37: dealsSurvived | L37: 18 | N37: When a {rank} lands correctly in this column → +2 coins | O37: rankCoin | P37: TEMPLATE
A38: Pillars | B38: Coin Gain | C38: per empty rank, most-held landing | D38: Deck Shaping | E38: Empty Ranks Coins | F38: heartZeroRanksCoin | G38: uncommon | H38: 6 | I38: no | J38: behavior | K38: removalsUsed | L38: 50 | N38: When your most-held rank ({rank}) lands in this column → +2 coins per rank with zero copies in your full deck | O38: heartZeroRanksCoin | P38: TEMPLATE
A39: Pillars | B39: Coin Gain | C39: per ♥ top at end | E39: Envy | F39: envy | G39: uncommon | H39: 6 | I39: no | J39: milestone | K39: runsPlayed | L39: 5 | N39: At deal end → +2 coins per pile in this column with a ♥ | O39: heartPiles
A40: Pillars | B40: Coin Gain | C40: only pillar equipped | D40: Loadout | E40: Greedy | F40: greedy | G40: uncommon | H40: 6 | I40: no | J40: milestone | K40: dealsSurvived | L40: 6 | N40: At deal end if only equipped pillar → +1 coin per 5 cards in your full deck | O40: greedy
A41: Pillars | B41: Coin Gain | C41: if all survive | E41: Guardian | F41: columnGuardian | G41: uncommon | H41: 6 | I41: yes | N41: At deal end if every pile in this column survived → +4 coins | O41: columnAllAlive
A42: Pillars | B42: Coin Gain | C42: per suit landing | E42: Heart Bonus | F42: heartBounty | G42: common | H42: 6 | I42: yes | N42: When a ♥ lands in this column → +1 coin | O42: suitBounty
A43: Pillars | B43: Coin Gain | C43: if one pile survives | E43: Insurance | F43: insurance | G43: uncommon | H43: 6 | I43: no | J43: behavior | K43: pilesLost | L43: 55 | N43: At deal end if only one pile is alive → +8 coins | O43: insurance
A44: Pillars | B44: Coin Gain | C44: if none survive | E44: Last Licks | F44: lastLicks | G44: uncommon | H44: 6 | I44: no | J44: behavior | K44: pilesLost | L44: 18 | N44: At deal end if no pile in this column survived → +8 coins | O44: columnNoneAlive
A45: Pillars | B45: Coin Gain | C45: streak-grown | E45: Streak Coin | F45: streakCoin | G45: uncommon | H45: 6 | I45: yes | N45: From the 4th consecutive correct guess in this column → +1 coin per guess Resets on a wrong guess or a guess in another column | O45: streakCoin
A46: Bases | B46: Coin Gain | C46: doubles bonus, adds a curse | D46: Curse Payoff | E46: Devil's Deal | F46: devilsDeal | G46: uncommon | H46: 6 | I46: yes | N46: Double bonus coins earned this deal → add a curse to a top card in this column | O46: devilsDeal
A47: Bases | B47: Coin Gain | C47: kills ♥ piles for coins | D47: Pile Destruction | E47: Heart Demolish | F47: heartDemolish | G47: uncommon | H47: 6 | I47: no | J47: behavior | K47: heartsPlayed | L47: 90 | N47: Destroy every ♥-topped pile in this column → +4 coins per pile | O47: heartDemolish
A48: Bases | B48: Coin Gain | C48: per ♥ in the column's piles, buried included | E48: Heart Tax | F48: tax | G48: uncommon | H48: 6 | I48: yes | N48: +1 coin per ♥ card in this column's piles — every card, not just the tops | O48: tax
A49: Same-Powers | B49: Coin Gain | C49: per alive pile | E49: Dividend | F49: linkCoins | G49: uncommon | H49: 10 | I49: yes | N49: +1 coin per alive pile | O49: linkCoins
A51: Deal Control (2)
A52: Bases | B52: Deal Control | C52: clears an ambush instantly | E52: Escape Hatch | F52: ambushOut | G52: uncommon | H52: 6 | I52: no | J52: behavior | K52: ambushesWon | L52: 3 | N52: If in a Just a Two ambush → clear the deal instantly | O52: ambushWin
A53: Bases | B53: Deal Control | C53: buries the deck, wins the deal | D53: Bury | E53: Last Resort | F53: lastResort | G53: uncommon | H53: 6 | I53: no | J53: behavior | K53: pilesLost | L53: 75 | N53: If not a boss deal → bury the whole deck under a pile in this column and win instantly (destroys itself and any adjacent Base) | O53: lastResort
A55: Deck Removal (3)
A56: Pillars | B56: Deck Removal | C56: the column's last death purges the killer | D56: Deck Shaping | E56: Final Cut | F56: finalPilePurge | G56: uncommon | H56: 6 | I56: no | J56: behavior | K56: pilesLost | L56: 50 | N56: When the last pile in this column dies → permanently purge the card that killed it | O56: finalPilePurge
A57: Bases | B57: Deck Removal | C57: the chosen top card | D57: Pile Destruction | E57: Sacrifice | F57: sacrifice | G57: uncommon | H57: 6 | I57: yes | N57: Choose a pile → purge its top card from your deck, then kill that pile | O57: sacrifice
A58: Same-Powers | B58: Deck Removal | C58: granted per Same, chosen at deal end (experiment) | E58: Long Odds | F58: linkPurge | G58: uncommon | H58: 10 | I58: no | J58: behavior | K58: removalsUsed | L58: 14 | N58: At deal end → purge a card of your choice, one per correct Same | O58: linkPurge
A60: Loadout & Meta (4)
A61: Pillars | B61: Loadout & Meta | C61: wards a Two; cleanses cursed landings | D61: Curse Removal | E61: Bouncer | F61: twoWard | G61: uncommon | H61: 6 | I61: no | J61: behavior | K61: jokersPlayed | L61: 4 | N61: 50% chance to turn away a Just a Two mystery 100% if your full deck has no 2s When a cursed card lands in this column → remove that curse from the card | O61: twoWard
A62: Pillars | B62: Loadout & Meta | C62: mirrors the centre pillar | E62: Ditto | F62: ditto | G62: uncommon | H62: 6 | I62: no | J62: milestone | K62: runsWon | L62: 1 | N62: Mirror the center column's Pillar | O62: ditto
A63: Pillars | B63: Loadout & Meta | C63: finds the Queen; Queens pay on landing | D63: Coin Gain | E63: Queen-Finder | F63: queenFinder | G63: uncommon | H63: 6 | I63: no | J63: behavior | K63: jokersPlayed | L63: 6 | N63: +50% chance to find a Beheaded Queen at a mystery node 100% if Queens are your most-held rank When a Queen lands in this column → +1 coin | O63: queenFinder
A64: Bases | B64: Loadout & Meta | C64: recharges the other bases | E64: Reactor | F64: refreshBases | G64: uncommon | H64: 6 | I64: no | J64: behavior | K64: basesPlaced | L64: 25 | N64: Recharge your other two Bases | O64: refreshBases
A66: Pack (4)
A67: Packs | B67: Pack | C67: playing cards | E67: Large Card Pack | F67: cardPack | G67: uncommon | H67: 4 | I67: no | J67: milestone | K67: dealsWonRegular | L67: 15 | N67: Reveal 5 random cards — keep 2 to swap into your deck | O67: card
A68: Packs | B68: Pack | C68: stickers | E68: Large Sticker Pack | F68: largeStickerPack | G68: common | H68: 6 | I68: no | J68: behavior | K68: stickersApplied | L68: 50 | N68: Reveal 5 random stickers — keep 2 | O68: sticker
A69: Packs | B69: Pack | C69: playing cards | E69: Small Card Pack | F69: smallCardPack | G69: common | H69: 2 | I69: yes | N69: Reveal 3 random cards — keep 1 to swap into your deck | O69: card
A70: Packs | B70: Pack | C70: stickers | E70: Small Sticker Pack | F70: stickerPack | G70: common | H70: 3 | I70: yes | N70: Reveal 3 random stickers — keep 1 | O70: sticker
A72: Peek (12)
A73: Stickers | B73: Peek | C73: needs a base-free column | E73: Base Scout | F73: baseScout | G73: uncommon | H73: 3 | I73: no | J73: behavior | K73: basesPlaced | L73: 12 | N73: If in column with no Base → peek next card If this card kills its pile → this becomes a curse | O73: baseScout
A74: Stickers | B74: Peek | C74: needs a pillar-free column | E74: Pillar Scout | F74: pillarScout | G74: uncommon | H74: 3 | I74: no | J74: behavior | K74: pillarsPlaced | L74: 12 | N74: If in column with no Pillar → peek next card If this card kills its pile → this becomes a curse | O74: pillarScout
A75: Stickers | B75: Peek | C75: on landing; curse on kill | E75: Twin Spark | F75: twinSpark | G75: uncommon | H75: 3 | I75: no | J75: behavior | K75: zenGamesPlayed | L75: 4 | N75: Peek next card If this card kills its pile → this becomes a curse | O75: twinSpark
A76: Pillars | B76: Peek | C76: on a pile death | E76: Last Rites | F76: lastRites | G76: uncommon | H76: 6 | I76: no | J76: behavior | K76: dealsWonLegendary | L76: 1 | N76: When a pile in this column dies → peek next card | O76: lastRites
A77: Pillars | B77: Peek | C77: on a royal ♠ | E77: Queen's Eye | F77: queensEye | G77: uncommon | H77: 6 | I77: yes | N77: When a royal ♠ (J/Q/K) lands in this column → peek next card | O77: queensEye
A78: Bases | B78: Peek | C78: trades the deal's banked bonus | D78: Coin Loss | E78: Bonus Reset | F78: bonusResetPeek | G78: uncommon | H78: 6 | I78: no | J78: milestone | K78: coinsEarnedLifetime | L78: 80 | N78: Reset bonus coins earned this deal to 0 → peek next card | O78: bonusResetPeek
A79: Bases | B79: Peek | C79: destroys this column's pillar | D79: Loadout | E79: Demolish | F79: demolish | G79: uncommon | H79: 6 | I79: no | J79: behavior | K79: pillarsPlaced | L79: 18 | N79: Permanently destroy this column's Pillar → peek the next 3 cards | O79: demolish
A80: Bases | B80: Peek | C80: spends the whole purse | E80: Empty Purse | F80: emptyPurse | G80: uncommon | H80: 6 | I80: no | J80: milestone | K80: coinsEarnedLifetime | L80: 150 | N80: Spend all your coins → bury 1 card per 5 coins spent, then peek the next card | O80: emptyPurse
A81: Bases | B81: Peek | C81: kills a ♠ pile first | D81: Pile Destruction | E81: Kamikaze | F81: kamikaze | G81: uncommon | H81: 6 | I81: no | J81: milestone | K81: dealsWonLegendary | L81: 2 | N81: Kill a random ♠-topped pile in this column → peek the next 2 cards | O81: kamikaze
A82: Bases | B82: Peek | C82: peek the next card | E82: Lone Eye | F82: lonePeek | G82: uncommon | H82: 6 | I82: no | J82: behavior | K82: samesCalled | L82: 8 | N82: Peek the next card | O82: lonePeek
A83: Bases | B83: Peek | C83: needs an all-♠ column | E83: Spade Peeker | F83: spadePeek | G83: uncommon | H83: 6 | I83: no | J83: behavior | K83: zenHardWon | L83: 1 | N83: Peek the next X cards, where X is the number of piles in this column with a ♠ top card | O83: spadePeek
A84: Same-Powers | B84: Peek | C84: on a Same | E84: Same Peeker | F84: samePeek | G84: uncommon | H84: 10 | I84: yes | N84: Peek next card | O84: samePeek
A86: Pile Size & Score (7)
A87: Stickers | B87: Pile Size & Score | C87: score shelter | E87: Anchor | F87: anchor | G87: common | H87: 1 | I87: yes | N87: At deal end if top card → exclude from smallest-pile size | O87: anchor
A88: Stickers | B88: Pile Size & Score | C88: equalises the board; curse on kill | E88: Donate | F88: donate | G88: uncommon | H88: 3 | I88: yes | N88: Make all pile sizes equal If this card kills its pile → this becomes a curse | O88: donate
A89: Pillars | B89: Pile Size & Score | C89: ♦ tops excluded | E89: Diamond Anchor | F89: diamondAnchor | G89: uncommon | H89: 6 | I89: no | J89: behavior | K89: diamondsPlayed | L89: 200 | N89: At deal end → exclude each ♦-topped pile in this column from the smallest-pile score | O89: diamondAnchor
A90: Pillars | B90: Pile Size & Score | C90: equalises on a ♦ | E90: Diamond Distribution | F90: diamondDistribution | G90: uncommon | H90: 6 | I90: no | J90: behavior | K90: removalsUsed | L90: 10 | N90: When a ♦ lands in this column → make this column's piles equal size | O90: diamondDistribution
A91: Pillars | B91: Pile Size & Score | C91: an extra pile | E91: Fourth Seat | F91: fourthSeat | G91: uncommon | H91: 6 | I91: no | J91: milestone | K91: endlessStagesReached | L91: 1 | N91: This column starts each deal with 1 extra pile (max 4) | O91: columnPiles
A92: Pillars | B92: Pile Size & Score | C92: ♦ while broke; flat broke may purge | D92: Pauper, Deck Removal | E92: Pauper's Diamond | F92: pauperDiamondEqualize | G92: uncommon | H92: 6 | I92: yes | N92: If purse <10 coins → when a ♦ lands in this column make all piles the same size If 0 coins → optionally purge the top card of any pile board-wide | O92: pauperDiamondEqualize
A93: Bases | B93: Pile Size & Score | C93: equalises the whole board | E93: Ballast | F93: evenOut | G93: uncommon | H93: 6 | I93: yes | N93: Make every pile on the board equal size | O93: evenOut
A95: Safety & Saves (17)
A96: Stickers | B96: Safety & Saves | C96: carrier safe on a matched bet; curse on kill | E96: Guard | F96: suitImmunity | G96: uncommon | H96: 3 | I96: no | J96: behavior | K96: spadesPlayed | L96: 150 | N96: If another pile shows this suit → safe If this card kills its pile → this becomes a curse | O96: suitImmunity
A97: Stickers | B97: Safety & Saves | C97: rank-matched tie save; curse on kill | E97: Same-Safe | F97: tieSafe | G97: common | H97: 1 | I97: yes | N97: If another pile shows this rank → safe If this card kills its pile → this becomes a curse | O97: tieSafe
A98: Pillars | B98: Safety & Saves | C98: relaxes what survives a Same | D98: Same Shield & Power | E98: Close Call | F98: sameTolNear | G98: uncommon | H98: 6 | I98: no | J98: behavior | K98: correctSames | L98: 52 | N98: Same calls are safe on cards ±1 in value in this column — a survived Same counts as a full correct Same (charges the Same Shield, fires your Same-Power) | O98: sameTolerance
A99: Pillars | B99: Safety & Saves | C99: any tie, in column | E99: Column Tie-Safe | F99: columnTieSafe | G99: uncommon | H99: 6 | I99: no | J99: behavior | K99: samesCalled | L99: 12 | N99: Any tie is safe in this column | O99: columnTieSafe
A100: Pillars | B100: Safety & Saves | C100: majority suit | E100: Majority Rule | F100: suitMajoritySafe | G100: uncommon | H100: 6 | I100: no | J100: milestone | K100: bossesBeaten | L100: 6 | N100: If half or more of your full deck is {suit} → {suit} cards are safe when they land in this column | O100: suitMajoritySafe | P100: TEMPLATE
A101: Pillars | B101: Safety & Saves | C101: ♥ while broke; flat broke peeks | D101: Pauper, Peek | E101: Pauper's Heart | F101: pauperHeart | G101: uncommon | H101: 6 | I101: yes | N101: If purse <10 coins → when a ♥ lands in this column it is safe If 0 coins → peek next card | O101: pauperHeartSafe
A102: Pillars | B102: Safety & Saves | C102: neighbour rank at zero | D102: Deck Shaping | E102: Rank Gap | F102: rankGapSafe | G102: uncommon | H102: 6 | I102: no | J102: behavior | K102: removalsUsed | L102: 20 | N102: If a card lands in this column and your full deck holds zero copies of the rank above or below it → it is safe | O102: rankGapSafe
A103: Pillars | B103: Safety & Saves | C103: deck's commonest rank | E103: Rank Shield | F103: rankShield | G103: uncommon | H103: 6 | I103: yes | N103: The most common rank in your full deck ({rank}) is always safe in this column | O103: rankShield | P103: TEMPLATE
A104: Pillars | B104: Safety & Saves | C104: revive a dead pile | E104: Revive | F104: revive | G104: uncommon | H104: 6 | I104: no | J104: milestone | K104: dealsWonLegendary | L104: 4 | N104: When a pile in this column reaches 10 cards → revive one dead pile | O104: revive
A105: Pillars | B105: Safety & Saves | C105: relaxes what survives a Same | D105: Same Shield & Power | E105: Royal Pair | F105: sameTolRoyal | G105: uncommon | H105: 6 | I105: no | J105: behavior | K105: samesCalled | L105: 40 | N105: A royal landing on a royal survives a Same call in this column | O105: sameTolerance
A106: Pillars | B106: Safety & Saves | C106: royals, if no 2s in deck | E106: Royal Sanctuary | F106: royalSanctuary | G106: uncommon | H106: 6 | I106: no | J106: behavior | K106: removalsUsed | L106: 30 | N106: If your full deck has no 2s → royals (J/Q/K) are always safe in this column | O106: royalSafeNoTwos
A107: Pillars | B107: Safety & Saves | C107: relaxes what survives a Same | D107: Same Shield & Power | E107: Same Suit Safe | F107: sameTolSuit | G107: uncommon | H107: 6 | I107: yes | N107: A card landing on its own suit is safe in this column | O107: sameTolerance
A108: Pillars | B108: Safety & Saves | C108: deck's scarcest suit | E108: Scarce Suit | F108: suitShield | G108: uncommon | H108: 6 | I108: yes | N108: The suit your full deck holds the fewest of is safe when it lands in this column (ties → every tied suit) | O108: suitShieldDaily
A109: Pillars | B109: Safety & Saves | C109: chance to save a dying pile | E109: Second Wind | F109: secondWind | G109: uncommon | H109: 6 | I109: yes | N109: When a pile in this column dies → 25% chance to save it: the top card stays, the buried cards shuffle back into the deck | O109: secondWind
...

Sheet Inactive
A1: RETIRED items (`inactive: true`) — out of EVERY acquisition pool, but still registered: an old save's copy keeps resolving and firing, and the Collection shows them greyed. None of these count on the Summary.
A2: Class | B2: Outcome | C2: Outcome detail | D2: Also pays | E2: Item | F2: id | G2: Rarity | H2: Cost | I2: Unlocked at start | J2: Unlock type | K2: Unlock stat | L2: Unlock count | M2: Suit limit | N2: In-game help text | O2: Effect key | P2: Lint
A3: Retired | B3: Coin Gain | C3: if all column tops match | E3: All Hearts | F3: allHeartsCoin | G3: common | H3: 4 | I3: no | J3: milestone | K3: coinsEarnedLifetime | L3: 60 | N3: At deal end → +4 coins if every surviving pile in this column has a ♥ top card | O3: allSuitTop
A4: Retired | B4: Pile Size & Score | C4: ♦ piles in column | E4: Diamond Boost | F4: diamondBoost | G4: common | H4: 3 | I4: yes | N4: Every pile with a ♦ top card in this column → +3 pile size | O4: diamondBoost
A5: Retired | B5: Coin Gain | C5: on a kill | E5: Last Coin | F5: deathBounty | G5: common | H5: 2 | I5: yes | M5: ♥ | N5: +3 coins if it kills a pile | O5: deathBounty
A6: Retired | B6: Pile Size & Score | C6: while broke | D6: Pauper | E6: Pauper's Diamond | F6: pauperDiamond | G6: common | H6: 3 | I6: yes | N6: While your purse holds under 10 coins → a ♦ landing anywhere on the board counts +2 toward pile size instead of +1 | O6: pauperDiamondSize
A7: Retired | B7: Card Change | C7: counts as every suit | E7: Wild Suit | F7: wildSuit | G7: common | H7: 1 | I7: yes | N7: Counts as every suit | O7: wildSuit
A8: Retired | B8: Safety & Saves | C8: carrier safe on a matched bet; curse on kill | E8: Club Guard | F8: clubGuard | G8: uncommon | H8: 5 | I8: no | J8: behavior | K8: cardsBuried | L8: 120 | M8: ♣ | N8: Safe if this card lands on a ♣, or a ♣ lands on this card | O8: suitImmunity
A9: Retired | B9: Bury | C9: on ♣ contact | E9: Club Snob | F9: clubSnob | G9: uncommon | H9: 10 | I9: no | J9: behavior | K9: pilesLost | L9: 40 | M9: ♣ | N9: When a ♣ lands on this card, or this card lands on a ♣ → bury 1 deck card under the pile | O9: clubSnob
A10: Retired | B10: Bury | C10: scales with deck left | E10: Club Thin | F10: clubThin | G10: uncommon | H10: 6 | I10: no | J10: behavior | K10: cardsBuried | L10: 150 | N10: When a ♣ lands in this column → bury 1 card per 25 cards remaining in the deck | O10: clubThin
A11: Retired | B11: Coin Gain | C11: per other sticker | E11: Collector | F11: collector | G11: uncommon | H11: 1 | I11: no | J11: behavior | K11: stickersApplied | L11: 90 | M11: ♥ | N11: +1 coin per other sticker on this card | O11: collector
A12: Retired | B12: Coin Gain | C12: per deck card left | E12: Deep Pockets | F12: deepPockets | G12: uncommon | H12: 3 | I12: no | J12: milestone | K12: bestCoinsInClimb | L12: 140 | M12: ♥ | N12: +1 coin per 10 cards left in the deck | O12: deepPockets
A13: Retired | B13: Pile Size & Score | C13: per rank duplicate | E13: Diamond Echo | F13: diamondDupeSize | G13: uncommon | H13: 6 | I13: no | J13: behavior | K13: diamondsPlayed | L13: 150 | N13: When a ♦ lands in this column → +1 pile size per duplicate of that card's rank in your full deck | O13: diamondDupeSize
A14: Retired | B14: Safety & Saves | C14: carrier safe on a matched bet; curse on kill | E14: Diamond Guard | F14: diamondGuard | G14: uncommon | H14: 5 | I14: no | J14: milestone | K14: bestCoinsInClimb | L14: 100 | M14: ♦ | N14: Safe if this card lands on a ♦, or a ♦ lands on this card | O14: suitImmunity
A15: Retired | B15: Pile Size & Score | C15: while a pile is size 1 | E15: Diamond Lifeline | F15: sizeOneDiamonds | G15: uncommon | H15: 5 | I15: yes | N15: While any pile in this column has pile size 1 → a ♦ landing anywhere on the board counts +2 toward pile size instead of +1 | O15: sizeOneDiamonds
A16: Retired | B16: Shuffle | C16: every ♦-topped pile | E16: Diamond Ripple | F16: diamondRipple | G16: uncommon | H16: 2 | I16: no | J16: behavior | K16: perfectDeals | L16: 8 | M16: ♦ | N16: Shuffle every other pile with a ♦ top card | O16: diamondRipple
A17: Retired | B17: Pile Size & Score | C17: per empty rank, ♦ landing | D17: Deck Shaping | E17: Empty Ranks Heavy | F17: diamondZeroRanksSize | G17: uncommon | H17: 8 | I17: no | J17: behavior | K17: removalsUsed | L17: 60 | N17: When a ♦ lands in this column → +1 pile size per rank with zero copies in your full deck | O17: diamondZeroRanksSize
A18: Retired | B18: Coin Gain | C18: per buried card | E18: Excavator | F18: excavator | G18: uncommon | H18: 3 | I18: no | J18: behavior | K18: cardsBuried | L18: 60 | N18: At deal end → +1 coin per buried card in this column's largest pile with a ♥ top card | O18: excavator
A19: Retired | B19: Coin Gain | C19: coin flip | E19: Gambler | F19: gambler | G19: uncommon | H19: 5 | I19: no | J19: behavior | K19: jokersPlayed | L19: 12 | N19: At deal end → 50/50: +3 coins or nothing | O19: gambler
A20: Retired | B20: Coin Gain | C20: per ♥ top | E20: Heart Choir | F20: heartChoir | G20: uncommon | H20: 3 | I20: no | J20: behavior | K20: heartsPlayed | L20: 200 | M20: ♥ | N20: +1 coin per each pile with a ♥ top card | O20: heartChoir
A21: Retired | B21: Safety & Saves | C21: carrier safe on a matched bet; curse on kill | E21: Heart Guard | F21: heartGuard | G21: uncommon | H21: 5 | I21: no | J21: milestone | K21: dealsSurvived | L21: 25 | M21: ♥ | N21: Safe if this card lands on a ♥, or a ♥ lands on this card | O21: suitImmunity
A22: Retired | B22: Coin Gain | C22: on ♥ contact | E22: Heart Snob | F22: heartSnob | G22: uncommon | H22: 2 | I22: no | J22: behavior | K22: heartsPlayed | L22: 75 | M22: ♥ | N22: When a ♥ lands on this card, or this card lands on a ♥ → +2 coins | O22: heartSnob
A23: Retired | B23: Pile Size & Score | C23: conditional: +size to matching piles | E23: Heavy | F23: heavy | G23: uncommon | H23: 1 | I23: yes | N23: If another pile shows this suit → +1 pile size to every pile whose top matches, including this one If this card kills its pile → this becomes a curse | O23: heavy
A24: Retired | B24: Coin Gain | C24: random | E24: Loose Change | F24: looseChange | G24: uncommon | H24: 2 | I24: no | J24: milestone | K24: bestCoinsInClimb | L24: 60 | M24: ♥ | N24: +0–3 coins (random) | O24: looseChange
A25: Retired | B25: Pile Size & Score | C25: conditional: +size to matching piles | E25: Massive | F25: massive | G25: uncommon | H25: 2 | I25: no | J25: behavior | K25: stickersApplied | L25: 10 | M25: ♦ | N25: If another pile shows this suit → +2 pile size to every pile whose top matches, including this one If this card kills its pile → this becomes a curse | O25: heavy
A26: Retired | B26: Pile Size & Score | C26: ♦ count more | E26: Massive Diamond | F26: stickerCount | G26: uncommon | H26: 4 | I26: yes | N26: ♦ cards in this column count as +2 toward pile size | O26: heavyDiamond
A27: Retired | B27: Safety & Saves | C27: relaxes what survives a Same | D27: Same Shield & Power | E27: Perfect Ten | F27: sameTolSum10 | G27: uncommon | H27: 7 | I27: yes | N27: Ranks summing to 10 survive a Same call in this column. A survived Same counts as a full correct Same — charges the Same Shield and fires your Same-Power | O27: sameTolerance
A28: Retired | B28: Shuffle | C28: this pile, optional | E28: Shuffle | F28: shuffle | G28: uncommon | H28: 1 | I28: yes | M28: ♦ | N28: Optionally shuffle the pile | O28: shuffle
A29: Retired | B29: Peek | C29: on ♠ contact | E29: Spade Snob | F29: suitSnob | G29: uncommon | H29: 4 | I29: no | J29: behavior | K29: spadesPlayed | L29: 60 | M29: ♠ | N29: When a ♠ lands on this card, or this card lands on a ♠ → peek at the next card | O29: suitSnob
A30: Retired | B30: Bury | C30: sticker-free ♣ | E30: Clean Bury | F30: clubTribute | G30: rare | H30: 10 | I30: no | J30: behavior | K30: clubsPlayed | L30: 150 | N30: When a ♣ with no stickers lands in this column → bury 1 card under that pile | O30: clubTribute
A31: Retired | B31: Coin Gain | C31: streak-grown | E31: Compound | F31: compound | G31: rare | H31: 6 | I31: no | J31: milestone | K31: bestCampaignScore | L31: 120 | M31: ♥ | N31: +X coins. X starts at 0, grows by 1 each correct placement, resets to 0 on a wrong guess | O31: compound
A32: Retired | B32: Pile Size & Score | C32: column opens at size 8 | D32: Deck Shaping | E32: Crazy Eights | F32: eightStart | G32: rare | H32: 10 | I32: no | J32: behavior | K32: perfectDeals | L32: 12 | N32: If 8s are the most common rank in your full deck → this column's piles start at pile size 8 | O32: startPileSizeEight
A33: Retired | B33: Coin Gain | C33: highest ♥ top | E33: Highest Heart | F33: highestEven | G33: rare | H33: 8 | I33: no | J33: milestone | K33: bestCampaignScore | L33: 220 | N33: At deal end → earn coins equal to the highest numbered ♥ top card in this column (2–10 face value, Ace pays 1, royals pay 0) | O33: highestHeart
A34: Retired | B34: Coin Gain | C34: on prime ranks | E34: Prime | F34: prime | G34: rare | H34: 3 | I34: no | J34: milestone | K34: bossesBeaten | L34: 20 | N34: When a prime-rank card (2/3/5/7) lands correctly in this column → +1 coin | O34: prime
A35: Retired | B35: Deck Removal | C35: a whole rank, at purchase | D35: Deck Shaping | E35: Rank Purge | F35: purgeRank | G35: rare | H35: 6 | I35: yes | N35: On purchase → purge every {rank} from your deck (no effect during deal) | O35: purgeRank | P35: TEMPLATE
A36: Retired | B36: Bury | C36: per rank-matching top | E36: Rank Roots | F36: clubRoots | G36: rare | H36: 8 | I36: no | J36: behavior | K36: clubsPlayed | L36: 120 | M36: ♣ | N36: When this card lands → bury 1 card under each pile whose top card matches this card's rank | O36: clubRoots
A37: Retired | B37: Pile Size & Score | C37: board-wide + hub | E37: Same Heavy | F37: linkHeavy | G37: rare | H37: 9 | I37: no | J37: behavior | K37: perfectDeals | L37: 4 | N37: Add +1 pile size to every pile, and +3 to the pile you called Same on | O37: linkHeavy
A38: Retired | B38: Peek | C38: on landing | E38: Scout | F38: revealNext | G38: rare | H38: 10 | I38: no | J38: behavior | K38: zenEasyWon | L38: 2 | M38: ♠ | N38: Peek at the next deck card | O38: revealNext
A39: Retired | B39: Tell | C39: scales with ♠ tops | E39: Spade Whispers | F39: spadeWhispers | G39: rare | H39: 8 | I39: no | J39: behavior | K39: spadesPlayed | L39: 200 | M39: ♠ | N39: The next X cards show a hint (higher/lower/same), where X = other piles with a ♠ top card | O39: spadeWhispers
A40: Retired | B40: Peek | C40: 50% on a ♠ | E40: Static | F40: static | G40: rare | H40: 3 | I40: no | J40: behavior | K40: zenMediumWon | L40: 2 | N40: When a ♠ lands in this column → 50% chance to peek at the next card | O40: static
A41: Retired | B41: Pile Size & Score | C41: streak-grown | E41: Streak Size | F41: streakBank | G41: rare | H41: 4 | I41: no | J41: behavior | K41: perfectDeals | L41: 2 | N41: From the 3rd consecutive correct guess in this column → +1 pile size per guess. Resets on a wrong guess or any guess in another column | O41: streakSize
A42: Retired | B42: Card Change | C42: whole rank → one suit, at purchase | D42: Deck Shaping | E42: Transmute | F42: transmute | G42: rare | H42: 8 | I42: no | J42: milestone | K42: bossesBeaten | L42: 8 | N42: Change all {rank}s to {suit} | O42: transmute | P42: TEMPLATE
A43: Retired | B43: Bury | C43: if a suit is absent | D43: Deck Shaping | E43: Void Tribute | F43: absentSuitClubBury | G43: rare | H43: 8 | I43: no | J43: behavior | K43: clubsPlayed | L43: 200 | N43: If your full deck contains no {suit} → when a ♣ lands in this column, bury 2 cards under that pile | O43: absentSuitClubBury | P43: TEMPLATE

Sheet Legend
A1: How to read and group this workbook
A3: Sheet: All Items | B3: One row per ACTIVE item. The header row has AutoFilter — click any header arrow to filter. To group by outcome, filter or sort on the 'Outcome' column; to group by what a class offers, filter 'Class' too. Retired items are not here — see the Inactive sheet.
A4: Sheet: By Outcome | B4: The same ACTIVE rows pre-sorted into outcome groups with a heading and a count per group — for reading straight through rather than filtering.
A5: Sheet: Inactive | B5: The RETIRED items (`inactive: true`): out of every acquisition pool, but still registered so old saves keep resolving and firing them, and the Collection shows them greyed. They count nowhere on the Summary.
A6: Sheet: Summary | B6: Counts by class and by outcome, ACTIVE items only. Every number is a live COUNTIF/COUNTIFS over 'All Items', so it re-totals if rows are filtered out and re-added, or edited.
A8: Outcome | B8: What the item actually pays you in — its headline payoff. Derived from the item's stable effect id (never its name or prose), from one taxonomy shared with item-list.html.
A9: Outcome detail | B9: The specific shape of that payoff — when it fires, what it keys on.
A10: Also pays | B10: Secondary currencies. Kamikaze's primary outcome is Peek; it 'also pays' Pile Destruction.
A11: Class | B11: Stickers · Pillars · Bases · Same-Powers · Cursed Stickers · Packs.
A12: Rarity | B12: How often the store OFFERS it (common/uncommon/rare) — independent of price. Shaded per tier.
A13: Cost | B13: Store price in coins. Blank for cursed stickers, which are never sold.
A14: Unlocked at start | B14: yes = in every roll pool from a fresh save. no = gated behind the unlock columns.
A15: Unlock type / stat / count | B15: The gate: the lifetime stat and the threshold that opens the item.
... A22: Source of truth | B22: items.js at the repo root. Never edit this workbook to change the game — edit items.js and regenerate.
